mricluster/__init__.py
mricluster/cluster.py
mricluster/extractor.py
mricluster/mricluster.py
mricluster/pipeline.py
mricluster/reduce.py
mricluster-0.1.dist-info/METADATA
mricluster-0.1.dist-info/RECORD
mricluster-0.1.dist-info/WHEEL
mricluster-0.1.dist-info/top_level.txt
