Metadata-Version: 2.1
Name: mricluster
Version: 0.1
Summary: MRI image set clustering module based on Convolutional Neural Network model
Home-page: https://github.com/terrenceliu/MRI_Clustering
Author: Terrence Liu
Author-email: terrenceliu@rice.edu
License: MIT
Platform: UNKNOWN
Classifier: Development Status :: 2 - Pre-Alpha
Classifier: License :: OSI Approved :: MIT License
Classifier: Programming Language :: Python :: 3.6
Classifier: Topic :: Scientific/Engineering :: Medical Science Apps.
Requires-Dist: numpy
Requires-Dist: pandas
Requires-Dist: matplotlib
Requires-Dist: tensorflow-gpu
Requires-Dist: keras
